print_cuneiform/__init__.py
print_cuneiform/sumerian.py
print_cuneiform-0.5.0.dist-info/METADATA
print_cuneiform-0.5.0.dist-info/WHEEL
print_cuneiform-0.5.0.dist-info/entry_points.txt
print_cuneiform-0.5.0.dist-info/licenses/LICENSE
print_cuneiform-0.5.0.dist-info/RECORD
