Metadata-Version: 2.1
Name: print_cuneiform
Version: 0.5.0
Summary: A small package for printing numbers as cuneiform
Project-URL: Homepage, https://gitlab.com/fhagelskjaer/print_cuneiform
Project-URL: Bug Tracker, https://gitlab.com/fhagelskjaer/print_cuneiform/-/issues
Author-email: Frederik Hagelskjaer <frederikhagel@gmail.com>
License-File: LICENSE
Keywords: sumerian,unicode
Classifier: Development Status :: 3 - Alpha
Classifier: License :: OSI Approved :: MIT License
Classifier: Operating System :: OS Independent
Classifier: Programming Language :: Python :: 3
Requires-Python: >=3
